gbkviz/__version__.py
gbkviz/align_coord.py
gbkviz/draw_genbank_fig.py
gbkviz/gbkviz_demo.gif
gbkviz/gbkviz_webapp.py
gbkviz/genbank/JX128258.1.gbk
gbkviz/genbank/MH051335.1.gbk
gbkviz/genbank/MH816966.1.gbk
gbkviz/genbank/MK373776.1.gbk
gbkviz/genbank.py
gbkviz/genome_align.py
gbkviz/scripts/launch_gbkviz_webapp.py
gbkviz/toppage.md
gbkviz/util.py
gbkviz-1.2.0.dist-info/entry_points.txt
gbkviz-1.2.0.dist-info/LICENSE
gbkviz-1.2.0.dist-info/WHEEL
gbkviz-1.2.0.dist-info/METADATA
gbkviz-1.2.0.dist-info/RECORD
