Metadata-Version: 2.1
Name: gbkviz
Version: 1.2.0
Summary: Simple web application to visualize and compare genomes in Genbank files
Home-page: https://github.com/moshi4/GBKviz/
License: MIT
Keywords: gbkviz,bioinformatics,streamlit,genomics,visualization
Author: moshi
Requires-Python: >=3.8,<4.0
Classifier: Intended Audience :: Science/Research
Classifier: License :: OSI Approved :: MIT License
Classifier: Programming Language :: Python :: 3
Classifier: Programming Language :: Python :: 3.10
Classifier: Programming Language :: Python :: 3.8
Classifier: Programming Language :: Python :: 3.9
Classifier: Topic :: Scientific/Engineering :: Bio-Informatics
Requires-Dist: biopython (>=1.79,<2.0)
Requires-Dist: reportlab (>=3.5.68,<4.0.0)
Requires-Dist: streamlit (==1.8.1)
Project-URL: Repository, https://github.com/moshi4/GBKviz/
